Workbook

Sheet Исходные данные
A1: ЧЕРНОВОЙ ИНЖЕНЕРНЫЙ КОМПЛЕКТ. Черновой инженерный комплект. Не является рабочим КЖ-проектом и не предназначен для выполнения строительных работ без проверки, корректировки и выпуска лицензированным инженером-конструктором.
A5: Объект | B5: Полностью подземное гражданское укрытие 3,0х4,0 м (в свету)
A6: Местоположение | B6: г. Киев, Русановские сады (частный участок)
A7: Дата | B7: 12.09.2026
A9: Параметр | B9: Код | C9: Значение
A10: Внутренняя длина, мм | B10: IN_L | C10: 4000
A11: Внутренняя ширина, мм | B11: IN_W | C11: 3000
A12: Чистая высота, мм | B12: IN_H | C12: 2200
A13: Толщина стен, мм | B13: WALL_T | C13: 300
A14: Толщина верхней плиты, мм | B14: TOP_SLAB_T | C14: 400
A15: Толщина нижней плиты (сцен. A), мм | B15: BOT_SLAB_T | C15: 350
A16: Толщина нижней плиты (сцен. B, усил.), мм | B16: BOT_SLAB_T_B | C16: 400
A17: Грунт над верхней плитой, мм | B17: SOIL_OVER_TOP | C17: 100
A18: Проём входа, мм | B18: ENTRY_OPENING | C18: 900
A19: Аварийный люк, мм | B19: HATCH | C19: 800x800
A20: Количество людей | B20: PEOPLE | C20: 4
A22: Наружная длина (=IN_L+2*WALL_T), мм | C22: =C10+2*C13
A23: Наружная ширина (=IN_W+2*WALL_T), мм | C23: =C11+2*C13
A24: Общая глубина (=SOIL+TOP+IN_H+BOT_A), мм | C24: =C17+C14+C12+C15
A26: Материалы (предварительно)
A27: Бетон: C35/45 W12 F200
A28: Арматура: A500C
A29: Стены: Ø12/150 верт.+гориз., 2 сетки
A30: Плиты (верх/низ): Ø14/150х150, верх+низ сетки
A31: Усиление проёмов: Ø16 (предварительно)
A33: ОТСУТСТВУЮЩИЕ ИСХОДНЫЕ ДАННЫЕ (обязательны до рабочего проекта)
A34: - Инженерно-геологические изыскания (литология, УГВ, физ-мех. св-ва грунтов)
A35: - Уровень грунтовых вод (сезонный максимум)
A36: - Плотность и угол внутреннего трения грунта обратной засыпки
A37: - Расчётное сопротивление основания R0
A38: - Фактическая отметка участка, геодезическая привязка
... A41: - Паспортные данные выбранных дверей и люка

Sheet Бетон
A1: ЧЕРНОВОЙ ИНЖЕНЕРНЫЙ КОМПЛЕКТ. Черновой инженерный комплект. Не является рабочим КЖ-проектом и не предназначен для выполнения строительных работ без проверки, корректировки и выпуска лицензированным инженером-конструктором.
A5: Класс бетона: C35/45 W12 F200 (предварительно)
A7: Площадь наружная, м2 | C7: =('Исходные данные'!C22/1000)*('Исходные данные'!C23/1000)
A8: Площадь внутренняя, м2 | C8: =('Исходные данные'!C10/1000)*('Исходные данные'!C11/1000)
A9: Площадь стен в плане, м2 | C9: =Бетон!C7-Бетон!C8
A11: Элемент | B11: Толщина/высота, мм | C11: Формула объёма | D11: Объём, м3 | E11: Класс бетона | F11: Примечание
A12: Нижняя плита (сцен. A) | B12: ='Исходные данные'!C15 | C12: площ.наруж x B12/1000 | D12: =Бетон!C7*(B12/1000) | E12: C35/45 W12 F200 | F12: по сценарию A
A13: Нижняя плита (сцен. B, усил.) | B13: ='Исходные данные'!C16 | C13: площ.наруж x B13/1000 | D13: =Бетон!C7*(B13/1000) | E13: C35/45 W12 F200 | F13: по сценарию B
A14: Стены | B14: ='Исходные данные'!C12 | C14: площ.стен x B14/1000 | D14: =Бетон!C9*(B14/1000) | E14: C35/45 W12 F200 | F14: чистая высота
A15: Верхняя плита | B15: ='Исходные данные'!C14 | C15: площ.наруж x B15/1000 | D15: =Бетон!C7*(B15/1000) | E15: C35/45 W12 F200
A16: Входная шахта (предв.) | D16: 1.8 | E16: C35/45 W12 F200 | F16: предварительно, укрупнённо
A17: Аварийная шахта (предв.) | D17: 0.9 | E17: C35/45 W12 F200 | F17: предварительно, укрупнённо
A18: Технологический резерв | D18: 0.85 | E18: C35/45 W12 F200 | F18: предварительно, укрупнённо
A19: ИТОГО (заказ, сценарий A нижней плиты) | D19: =D12+D14+D15+SUM(D16:D18)
A21: Примечание: объёмы — предварительные (укрупнённая методика). Наружная гидроизоляция
A22: невозможна -> рассматривать как 'белую ванну' (см. README).

Sheet Арматура
A1: ЧЕРНОВОЙ ИНЖЕНЕРНЫЙ КОМПЛЕКТ. Черновой инженерный комплект. Не является рабочим КЖ-проектом и не предназначен для выполнения строительных работ без проверки, корректировки и выпуска лицензированным инженером-конструктором.
A6: Класс арматуры | B6: A500C
A7: Шаг основной арматуры, мм | B7: 150
A8: Линейная масса Ø12, кг/м | B8: 0.888
A9: Линейная масса Ø14, кг/м | B9: 1.208
A10: Линейная масса Ø16, кг/м | B10: 1.578
A12: Периметр стен по осям, м | B12: =2*(('Исходные данные'!C22-'Исходные данные'!C13)+('Исходные данные'!C23-'Исходные данные'!C13))/1000
A13: Длина верт. стержня (высота+2х300 анкеровка), м | B13: =('Исходные данные'!C12+600)/1000
A14: Число верт. стержней на 1 сетку | B14: =ROUND(Арматура!B12*1000/Арматура!B7,0)+1
A15: Число гориз. стержней на 1 сетку (по высоте) | B15: =ROUND('Исходные данные'!C12/Арматура!B7,0)+1
A16: Длина 1 гориз. стержня (периметр+нахлёст 0.3м), м | B16: =Арматура!B12+0.3
A18: Поз. | B18: Ø, мм | C18: Назначение | D18: Кол-во стержней | E18: Длина стержня, м | F18: Общая длина, м | G18: Масса, кг
A19: 1 | B19: 12 | C19: Стены верт. (2 сетки) | D19: =2*Арматура!B14 | E19: =Арматура!B13 | F19: =D19*E19 | G19: =F19*Арматура!B8
A20: 2 | B20: 12 | C20: Стены гориз. (2 сетки) | D20: =2*Арматура!B15 | E20: =Арматура!B16 | F20: =D20*E20 | G20: =F20*Арматура!B8
A21: 3 | B21: 12 | C21: Угловые/доборные эл-ты стен (~8%, предв.) | G21: =0.08*(G19+G20)
A22: 4 | B22: 14 | C22: Верхняя плита, сетка верх+низ | D22: =2*((ROUND('Исходные данные'!C23/Арматура!B7,0)+1)+(ROUND('Исходные данные'!C22/Арматура!B7,0)+1)) | F22: =2*((ROUND('Исходные данные'!C23/Арматура!B7,0)+1)*'Исходные данные'!C22/1000+(ROUND('Исходные данные'!C22/Арматура!B7,0)+1)*'Исходные данные'!C23/1000) | G22: =F22*Арматура!B9
A23: 5 | B23: 14 | C23: Нижняя плита, сетка верх+низ | D23: =2*((ROUND('Исходные данные'!C23/Арматура!B7,0)+1)+(ROUND('Исходные данные'!C22/Арматура!B7,0)+1)) | F23: =2*((ROUND('Исходные данные'!C23/Арматура!B7,0)+1)*'Исходные данные'!C22/1000+(ROUND('Исходные данные'!C22/Арматура!B7,0)+1)*'Исходные данные'!C23/1000) | G23: =F23*Арматура!B9
A24: 6 | B24: 16 | C24: Усиление проёма входа (4х1.5м, предв.) | D24: 4 | E24: 1.5 | F24: =D24*E24 | G24: =F24*Арматура!B10
A25: 7 | B25: 16 | C25: Усиление проёма авар. люка (4х1.5м, предв.) | D25: 4 | E25: 1.5 | F25: =D25*E25 | G25: =F25*Арматура!B10
A26: 8 | C26: Монтажная арматура (фиксаторы, ~3%) | G26: =0.03*(G19+G20+G22+G23)
A27: 9 | C27: Технологический запас (~5%) | G27: =0.05*(G19+G20+G22+G23+G24+G25+G21+G26)
C28: ВСЕГО, кг | G28: =SUM(G19:G27)
C29: ВСЕГО, т | G29: =G28/1000
A31: Ориентир ТЗ: ~2,4 т — сверить после разработки рабочих чертежей.

Sheet Земляные работы
A1: ЧЕРНОВОЙ ИНЖЕНЕРНЫЙ КОМПЛЕКТ. Черновой инженерный комплект. Не является рабочим КЖ-проектом и не предназначен для выполнения строительных работ без проверки, корректировки и выпуска лицензированным инженером-конструктором.
A6: Отступ котлована от короба на сторону, м | B6: 1
A7: Запас по глубине (рабочее пространство), м | B7: 0.3
A9: Длина котлована, м | B9: =('Исходные данные'!C22/1000)+2*'Земляные работы'!B6
A10: Ширина котлована, м | B10: =('Исходные данные'!C23/1000)+2*'Земляные работы'!B6
A11: Глубина котлована, м | B11: =('Исходные данные'!C17+'Исходные данные'!C14+'Исходные данные'!C12+'Исходные данные'!C15)/1000+'Земляные работы'!B7
A12: Объём котлована, м3 | B12: ='Земляные работы'!B9*'Земляные работы'!B10*'Земляные работы'!B11
A13: Объём обратной засыпки (~40% от котлована), м3 | B13: =0.4*'Земляные работы'!B12
A14: Вывоз излишков грунта, м3 | B14: ='Земляные работы'!B12-'Земляные работы'!B13
A16: Статья | B16: LOW, грн | C16: REALISTIC, грн | D16: HIGH, грн
A17: Земляные работы: разработка котлована, вывоз/размещение грунта, обратная засыпка (объём котлована ~130 м3, ориентировочно) | B17: 55000 | C17: 90000 | D17: 140000
A18: ПОДЫТОГ (A) | B18: =SUM(B17:B17) | C18: =SUM(C17:C17) | D18: =SUM(D17:D17)

Sheet Двери и люки
A1: ЧЕРНОВОЙ ИНЖЕНЕРНЫЙ КОМПЛЕКТ. Черновой инженерный комплект. Не является рабочим КЖ-проектом и не предназначен для выполнения строительных работ без проверки, корректировки и выпуска лицензированным инженером-конструктором.
A6: Наименование | B6: Ед. | C6: Кол-во | D6: LOW цена/ед | E6: REALISTIC цена/ед | F6: HIGH цена/ед | G6: LOW сумма | H6: REALISTIC сумма | I6: HIGH сумма | J6: Примечание
A7: Наружная защитно-герметичная дверь (проём 900мм) | B7: шт | C7: 1 | D7: 40000 | E7: 60000 | F7: 90000 | G7: =C7*D7 | H7: =C7*E7 | I7: =C7*F7 | J7: тип и посадочные размеры уточнить по паспорту изделия
A8: Внутренняя герметичная дверь | B8: шт | C8: 1 | D8: 15000 | E8: 28000 | F8: 45000 | G8: =C8*D8 | H8: =C8*E8 | I8: =C8*F8 | J8: тип уточнить по паспорту изделия
A9: Металлическая рамка + крышка люка 800х800 | B9: компл | C9: 1 | D9: 7000 | E9: 12000 | F9: 18000 | G9: =C9*D9 | H9: =C9*E9 | I9: =C9*F9 | J9: тип уточнить по паспорту
A10: Закладные детали и герметизация проёмов | B10: компл | C10: 1 | D10: 3000 | E10: 5000 | F10: 7000 | G10: =C10*D10 | H10: =C10*E10 | I10: =C10*F10
A11: ИТОГО | G11: =SUM(G7:G10) | H11: =SUM(H7:H10) | I11: =SUM(I7:I10)

Sheet Вентиляция
A1: ЧЕРНОВОЙ ИНЖЕНЕРНЫЙ КОМПЛЕКТ. Черновой инженерный комплект. Не является рабочим КЖ-проектом и не предназначен для выполнения строительных работ без проверки, корректировки и выпуска лицензированным инженером-конструктором.
A6: Количество людей | B6: ='Исходные данные'!C20
A7: Норма воздухообмена на 1 чел., м3/ч (мин-макс) | B7: 15 | C7: 25
A8: Требуемый воздухообмен, м3/ч (мин-макс) | B8: =B7*B6 | C8: =C7*B6
A10: Вариант | B10: Оборудование | C10: Мощность | D10: LOW, грн | E10: REALISTIC, грн | F10: HIGH, грн | G10: Плюсы | H10: Минусы
A11: A. Базовая принудительная | B11: приточно-вытяжные вентиляторы, обратные клапаны, фильтр G4, ручной резерв | C11: ~60-100 м3/ч, ~40-80 Вт | D11: 35000 | E11: 80000 | F11: 80000 | G11: просто, недорого | H11: нет защиты от ОВ/пыли/дыма
A12: B. Специализир. ФВУ | B12: фильтровентиляционная установка, противовзрывные клапаны, фильтр аэрозоль+сорбция | C12: ~100-150 м3/ч, ~80-150 Вт | D12: 80000 | E12: 80000 | F12: 220000 | G12: выше защита воздуха | H12: дороже, сложнее
A14: Обязательно во всех вариантах: датчик CO2, датчик CO, дымовой датчик, ручной резервный привод.

Sheet Электрика
A1: ЧЕРНОВОЙ ИНЖЕНЕРНЫЙ КОМПЛЕКТ. Черновой инженерный комплект. Не является рабочим КЖ-проектом и не предназначен для выполнения строительных работ без проверки, корректировки и выпуска лицензированным инженером-конструктором.
A6: Наименование | B6: Ед. | C6: Кол-во | D6: LOW цена/ед | E6: REALISTIC цена/ед | F6: HIGH цена/ед | G6: LOW сумма | H6: REALISTIC сумма | I6: HIGH сумма | J6: Примечание
A7: Ввод 230В, вводной автомат, УЗО | B7: компл | C7: 1 | D7: 8000 | E7: 12000 | F7: 18000 | G7: =C7*D7 | H7: =C7*E7 | I7: =C7*F7
A8: Электрощит в сборе (автоматы, УЗО линий) | B8: компл | C8: 1 | D8: 7000 | E8: 12000 | F8: 20000 | G8: =C8*D8 | H8: =C8*E8 | I8: =C8*F8
A9: Кабельная разводка (силовая+освещение) | B9: компл | C9: 1 | D9: 10000 | E9: 18000 | F9: 27000 | G9: =C9*D9 | H9: =C9*E9 | I9: =C9*F9
A10: LED освещение (основное) | B10: компл | C10: 1 | D10: 4000 | E10: 7000 | F10: 12000 | G10: =C10*D10 | H10: =C10*E10 | I10: =C10*F10
A11: Аварийное освещение (авт. включение) | B11: компл | C11: 1 | D11: 3000 | E11: 6000 | F11: 10000 | G11: =C11*D11 | H11: =C11*E11 | I11: =C11*F11
A12: Розетки + USB-C блоки | B12: компл | C12: 1 | D12: 3000 | E12: 5000 | F12: 8000 | G12: =C12*D12 | H12: =C12*E12 | I12: =C12*F12
A13: ИТОГО | G13: =SUM(G7:G12) | H13: =SUM(H7:H12) | I13: =SUM(I7:I12)

Sheet Аккумулятор
A1: ЧЕРНОВОЙ ИНЖЕНЕРНЫЙ КОМПЛЕКТ. Черновой инженерный комплект. Не является рабочим КЖ-проектом и не предназначен для выполнения строительных работ без проверки, корректировки и выпуска лицензированным инженером-конструктором.
A6: Инвертор, кВт | B6: 5
A7: АКБ базовый вариант, кВт*ч | B7: 5
A8: АКБ расширенный вариант, кВт*ч | B8: 10
A10: Потребитель | B10: Мощность, Вт | C10: Автономность 5 кВт*ч, ч | D10: Автономность 10 кВт*ч, ч
A11: Вентиляция (вариант A) | B11: 60 | C11: =Аккумулятор!B7*1000/B11 | D11: =Аккумулятор!B8*1000/B11
A12: Освещение LED | B12: 40 | C12: =Аккумулятор!B7*1000/B12 | D12: =Аккумулятор!B8*1000/B12
A13: Телефоны (заряд, 4 шт.) | B13: 20 | C13: =Аккумулятор!B7*1000/B13 | D13: =Аккумулятор!B8*1000/B13
A14: Радиостанция | B14: 15 | C14: =Аккумулятор!B7*1000/B14 | D14: =Аккумулятор!B8*1000/B14
A15: Небольшой насос (циклично, ср.) | B15: 80 | C15: =Аккумулятор!B7*1000/B15 | D15: =Аккумулятор!B8*1000/B15
A17: Примечание: автономность указана отдельно по каждому потребителю (не суммарно).
A19: Позиция | B19: LOW, грн | C19: REALISTIC, грн | D19: HIGH, грн
A20: Гибридный инвертор 5 кВт | B20: 32000 | C20: 45000 | D20: 62000
A21: АКБ 5 кВт*ч (базовый) | B21: 45000 | C21: 65000 | D21: 95000
A22: АКБ 10 кВт*ч (расширенный, отдельный расчёт) | B22: 72000 | C22: 115000 | D22: 165000

Sheet Вода
A1: ЧЕРНОВОЙ ИНЖЕНЕРНЫЙ КОМПЛЕКТ. Черновой инженерный комплект. Не является рабочим КЖ-проектом и не предназначен для выполнения строительных работ без проверки, корректировки и выпуска лицензированным инженером-конструктором.
A6: Норма питья, л/чел/сутки | B6: 3
A7: Дней автономности | B7: 3
A8: Минимальный запас, л (=норма x чел x дней) | B8: =Вода!B6*'Исходные данные'!C20*Вода!B7
A9: Практический запас, л | B9: 100
A10: Предпочтительный запас, л (диапазон) | B10: 150 | C10: 200
A12: Наименование | B12: Ед. | C12: Кол-во | D12: LOW цена/ед | E12: REALISTIC цена/ед | F12: HIGH цена/ед | G12: LOW сумма | H12: REALISTIC сумма | I12: HIGH сумма | J12: Примечание
A13: Пищевая ёмкость 150-200л + кран | B13: компл | C13: 1 | D13: 3000 | E13: 5000 | F13: 9000 | G13: =C13*D13 | H13: =C13*E13 | I13: =C13*F13
A14: Небольшой насос | B14: шт | C14: 1 | D14: 2000 | E14: 4000 | F14: 7000 | G14: =C14*D14 | H14: =C14*E14 | I14: =C14*F14
A15: Канистры питьевой воды (НЗ) | B15: компл | C15: 1 | D15: 1500 | E15: 3000 | F15: 5000 | G15: =C15*D15 | H15: =C15*E15 | I15: =C15*F15
A16: Ручной резерв (помпа/самотёк) | B16: компл | C16: 1 | D16: 1500 | E16: 3000 | F16: 5000 | G16: =C16*D16 | H16: =C16*E16 | I16: =C16*F16
A17: ИТОГО | G17: =SUM(G13:G16) | H17: =SUM(H13:H16) | I17: =SUM(I13:I16)

Sheet Санитария
A1: ЧЕРНОВОЙ ИНЖЕНЕРНЫЙ КОМПЛЕКТ. Черновой инженерный комплект. Не является рабочим КЖ-проектом и не предназначен для выполнения строительных работ без проверки, корректировки и выпуска лицензированным инженером-конструктором.
A6: Наименование | B6: Ед. | C6: Кол-во | D6: LOW цена/ед | E6: REALISTIC цена/ед | F6: HIGH цена/ед | G6: LOW сумма | H6: REALISTIC сумма | I6: HIGH сумма | J6: Примечание
A7: Кассетный/химический биотуалет | B7: шт | C7: 1 | D7: 3000 | E7: 6000 | F7: 10000 | G7: =C7*D7 | H7: =C7*E7 | I7: =C7*F7
A8: Санитарная перегородка | B8: компл | C8: 1 | D8: 1000 | E8: 2000 | F8: 4000 | G8: =C8*D8 | H8: =C8*E8 | I8: =C8*F8
A9: Запас реагента | B9: компл | C9: 1 | D9: 500 | E9: 1000 | F9: 1500 | G9: =C9*D9 | H9: =C9*E9 | I9: =C9*F9
A10: Пакеты для биотуалета (запас) | B10: компл | C10: 1 | D10: 300 | E10: 500 | F10: 1000 | G10: =C10*D10 | H10: =C10*E10 | I10: =C10*F10
A11: Дезинфицирующие средства | B11: компл | C11: 1 | D11: 200 | E11: 500 | F11: 1500 | G11: =C11*D11 | H11: =C11*E11 | I11: =C11*F11
A12: ИТОГО | G12: =SUM(G7:G11) | H12: =SUM(H7:H11) | I12: =SUM(I7:I11)

Sheet Оснащение
A1: ЧЕРНОВОЙ ИНЖЕНЕРНЫЙ КОМПЛЕКТ. Черновой инженерный комплект. Не является рабочим КЖ-проектом и не предназначен для выполнения строительных работ без проверки, корректировки и выпуска лицензированным инженером-конструктором.
A6: Наименование | B6: Ед. | C6: Кол-во | D6: LOW цена/ед | E6: REALISTIC цена/ед | F6: HIGH цена/ед | G6: LOW сумма | H6: REALISTIC сумма | I6: HIGH сумма | J6: Примечание
A7: 2х-ярусная металлическая кровать | B7: шт | C7: 2 | D7: 6000 | E7: 10000 | F7: 17000 | G7: =C7*D7 | H7: =C7*E7 | I7: =C7*F7 | J7: альт.: 4 складные койки
A8: Стол / место отдыха | B8: шт | C8: 1 | D8: 2000 | E8: 4000 | F8: 7000 | G8: =C8*D8 | H8: =C8*E8 | I8: =C8*F8
A9: Металлические стеллажи | B9: шт | C9: 2 | D9: 2000 | E9: 3500 | F9: 6000 | G9: =C9*D9 | H9: =C9*E9 | I9: =C9*F9
A10: Аптечка | B10: компл | C10: 1 | D10: 1500 | E10: 3000 | F10: 6000 | G10: =C10*D10 | H10: =C10*E10 | I10: =C10*F10
A11: Огнетушители | B11: шт | C11: 2 | D11: 1000 | E11: 1500 | F11: 2500 | G11: =C11*D11 | H11: =C11*E11 | I11: =C11*F11
A12: Инструменты (набор) | B12: компл | C12: 1 | D12: 3000 | E12: 6000 | F12: 10000 | G12: =C12*D12 | H12: =C12*E12 | I12: =C12*F12
A13: Средства связи (радиостанция) | B13: шт | C13: 1 | D13: 2000 | E13: 4000 | F13: 8000 | G13: =C13*D13 | H13: =C13*E13 | I13: =C13*F13
A14: Датчик CO2 | B14: шт | C14: 1 | D14: 2000 | E14: 4000 | F14: 7000 | G14: =C14*D14 | H14: =C14*E14 | I14: =C14*F14
A15: Датчик CO | B15: шт | C15: 1 | D15: 1500 | E15: 3000 | F15: 6000 | G15: =C15*D15 | H15: =C15*E15 | I15: =C15*F15
A16: Дымовой датчик | B16: шт | C16: 1 | D16: 500 | E16: 1000 | F16: 2000 | G16: =C16*D16 | H16: =C16*E16 | I16: =C16*F16
A17: ИТОГО | G17: =SUM(G7:G16) | H17: =SUM(H7:H16) | I17: =SUM(I7:I16)

Sheet Смета
A1: ЧЕРНОВОЙ ИНЖЕНЕРНЫЙ КОМПЛЕКТ. Черновой инженерный комплект. Не является рабочим КЖ-проектом и не предназначен для выполнения строительных работ без проверки, корректировки и выпуска лицензированным инженером-конструктором.
A6: № | B6: Раздел | C6: LOW, грн | D6: REALISTIC, грн | E6: HIGH, грн | F6: Источник
A7: A | B7: Земляные работы | C7: ='Земляные работы'!B18 | D7: ='Земляные работы'!C18 | E7: ='Земляные работы'!D18 | F7: Котлован, вывоз/засыпка грунта
A8: B | B8: Бетон | C8: =Бетон!D19*4500 | D8: =Бетон!D19*6000 | E8: =Бетон!D19*8000 | F8: объём х цена/м3 (LOW 4500 / REAL 6000 / HIGH 8000 грн/м3)
A9: C | B9: Арматура (материал) | C9: =Арматура!G29*33000 | D9: =Арматура!G29*40000 | E9: =Арматура!G29*55000 | F9: масса х цена/т (LOW 33000 / REAL 40000 / HIGH 55000 грн/т)
A10: D | B10: Опалубка | C10: 63000 | D10: 110000 | E10: 170000 | F10: Опалубка стен, плит, входного и аварийного узлов (аренда/монтаж/демонтаж)
A11: E | B11: Арматурные работы | C11: 18640 | D11: 32620 | E11: 46600 | F11: Арматурные работы: заготовка, вязка, монтаж каркасов
A12: F | B12: Бетонирование | C12: 26000 | D12: 45000 | E12: 70000 | F12: Бетонирование: укладка, уплотнение, уход за бетоном, устройство рабочих швов
A13: G | B13: Насос бетона | C13: 10000 | D13: 18000 | E13: 30000 | F13: Бетононасос / подача бетона
A14: H | B14: Доставка | C14: 15000 | D14: 25000 | E14: 45000 | F14: Доставка материалов и техники на объект (Русановские сады)
A15: I | B15: Герметизация швов | C15: 25000 | D15: 50000 | E15: 90000 | F15: Герметизация швов: гидрошпонки, набухающие шнуры, инъекционные шланги, кристалли
A16: J | B16: Защитные двери | C16: ='Двери и люки'!G11 | D16: ='Двери и люки'!H11 | E16: ='Двери и люки'!I11 | F16: Защитные двери: 1 наружная защитно-герметичная + 1 внутренняя герметичная (проём
A17: K | B17: Аварийный люк | C17: 15000 | D17: 25000 | E17: 45000 | F17: Аварийный люк 800х800: металлическая рамка, крышка, герметизация, лестница
A18: L | B18: Вентиляция | C18: 35000 | D18: 80000 | E18: 220000 | F18: Вентиляция: REALISTIC = вариант A (базовая принудительная); HIGH = вариант B (сп
A19: M | B19: Электрика | C19: ='Электрика'!G13 | D19: ='Электрика'!H13 | E19: ='Электрика'!I13 | F19: Электрика: щит, УЗО, автоматы, кабели, освещение (основное+аварийное), розетки,
A20: N | B20: Инвертор | C20: =Аккумулятор!B20 | D20: =Аккумулятор!C20 | E20: =Аккумулятор!D20 | F20: Гибридный инвертор 5 кВт
A21: O | B21: Аккумулятор | C21: =Аккумулятор!B21 | D21: =Аккумулятор!C21 | E21: =Аккумулятор!D21 | F21: Аккумулятор LiFePO4, базовый вариант 5 кВт·ч (вариант 10 кВт·ч — отдельно, см. л
A22: P | B22: Вода | C22: =Вода!G17 | D22: =Вода!H17 | E22: =Вода!I17 | F22: Водоснабжение: ёмкость(и) ~150–200 л, насос, кран, канистры, ручной резерв
A23: Q | B23: Туалет | C23: ='Санитария'!G12 | D23: ='Санитария'!H12 | E23: ='Санитария'!I12 | F23: Туалет: кассетный/химический биотуалет, перегородка, реагент, пакеты
A24: R | B24: Спальные места | C24: 12000 | D24: 20000 | E24: 34000 | F24: Спальные места: 2 двухъярусные металлические кровати (альт. 4 складные койки)
A25: S | B25: Мебель/хранение | C25: 10000 | D25: 20000 | E25: 34000 | F25: Мебель и хранение: стеллажи, стол, полки
A26: T | B26: Датчики | C26: 6000 | D26: 12000 | E26: 22000 | F26: Датчики: CO2, CO, дым, температура/влажность
A27: U | B27: Инструменты | C27: 5000 | D27: 9000 | E27: 16000 | F27: Инструменты, аптечка, огнетушители, средства связи (базовый комплект)
A28: V | B28: Геология | C28: 15000 | D28: 25000 | E28: 42000 | F28: Инженерно-геологические изыскания (ОБЯЗАТЕЛЬНО перед рабочим проектом)
A29: W | B29: Проект КЖ | C29: 45000 | D29: 75000 | E29: 130000 | F29: Разработка рабочего проекта КЖ лицензированным инженером-конструктором
A30: X | B30: Технадзор | C30: 18000 | D30: 35000 | E30: 60000 | F30: Технический и авторский надзор на этапе строительства
B31: ПОДЫТОГ (A-X) | C31: =SUM(C7:C30) | D31: =SUM(D7:D30) | E31: =SUM(E7:E30)
A32: Y | B32: Резерв на непредвиденное (15%) | C32: =C31*0.15 | D32: =D31*0.15 | E32: =E31*0.15
B33: ИТОГО | C33: =C31+C32 | D33: =D31+D32 | E33: =E31+E32

Sheet Источники цен
A1: ЧЕРНОВОЙ ИНЖЕНЕРНЫЙ КОМПЛЕКТ. Черновой инженерный комплект. Не является рабочим КЖ-проектом и не предназначен для выполнения строительных работ без проверки, корректировки и выпуска лицензированным инженером-конструктором.
A6: Позиция | B6: Статус | C6: Источник / обоснование
A7: Бетон C35/45 W12F200, грн/м3 | B7: сверено веб-поиском (базовый ориентир) + экспертная оценка класса/добавок | C7: ukrbeton.com, transbetonstroy.com.ua (сентябрь 2026) — базовая цена от ~3051 грн/м3; для W12/F200 и доставки принят диапазон 4500-8000 грн/м3
A8: Арматура А500С Ø12, грн/м (-> грн/т) | B8: сверено веб-поиском | C8: bekas.com.ua: 33.53 грн/м за Ø12 А500С (сентябрь 2026) => ~37 800 грн/т; для др. диаметров и с учётом волатильности принят диапазон 33000-55000 грн/т
A9: Защитно-герметичные двери | B9: сверено веб-поиском (аналоги военного/двойного назначения) | C9: antifire.ua: модели 52000-70000 грн за дверь ДУ-III/ДУ-I; для частного укрытия принят более широкий диапазон 45000-100000 грн
A10: Гибридный инвертор 5кВт / АКБ LiFePO4 | B10: ориентировочно, конкретные цены в результатах поиска не найдены | C10: Оценка по общедоступным рыночным моделям (prom.ua, deps.ua, svoya-energy.com.ua), сентябрь 2026 — рекомендуется получить актуальные КП
A11: Земляные работы, опалубка, бетонирование, вентиляция (оборудование), электрика, мебель, сантехника | B11: экспертная оценка по аналогам | C11: Не проверялось прямым веб-поиском в рамках этого комплекта — требует коммерческих предложений подрядчиков

Sheet Риски
A1: ЧЕРНОВОЙ ИНЖЕНЕРНЫЙ КОМПЛЕКТ. Черновой инженерный комплект. Не является рабочим КЖ-проектом и не предназначен для выполнения строительных работ без проверки, корректировки и выпуска лицензированным инженером-конструктором.
A6: № | B6: Риск | C6: Последствие | D6: Рекомендация
A7: 1 | B7: Отсутствие инженерно-геологических изысканий | C7: Неверные допущения по УГВ, грунту, основанию -> ошибки в расчёте плиты, стен, всплытия | D7: Заказать изыскания ДО разработки рабочего проекта
A8: 2 | B8: Всплытие конструкции при высоком УГВ (FS~1,1-1,2 в предв. расчёте) | C8: Подъём/раскрытие швов, потеря герметичности, повреждение конструкций | D8: Уточнить УГВ; рассмотреть утяжеление, консоль плиты, анкеры
A9: 3 | B9: Невозможность мембранной гидроизоляции («белая ванна») | C9: Риск фильтрации через рабочие швы и трещины при отсутствии контроля качества бетона | D9: Гидрошпонки+инъекционные шланги+кристаллизующиеся добавки; строгий контроль швов
A10: 4 | B10: Отсутствие расчёта на боковое давление грунта по факту грунта участка | C10: Недостаточное/избыточное армирование стен | D10: Расчёт по фактическим γ, φ грунта после изысканий
A11: 5 | B11: Не определён класс защитного сооружения ЦЗ | C11: Толщины/армирование/двери могут не соответствовать требуемому классу защиты | D11: Определить класс защиты с проектировщиком до выпуска рабочего проекта
A12: 6 | B12: Конкретные двери/люк не подобраны (нет паспортов изделий) | C12: Несоответствие проёмов, закладных, посадочных мест реальному изделию | D12: Подобрать изделия и скорректировать проёмы/закладные по паспорту
A13: 7 | B13: Приблизительность объёмов бетона и арматуры (укрупнённая методика) | C13: Отклонение фактического расхода материалов от сметы | D13: Уточнить после разработки полных рабочих чертежей
A14: 8 | B14: Цены в смете ориентировочные (часть — веб-поиск, часть — экспертная оценка) | C14: Отклонение бюджета от рыночных цен на момент закупки | D14: Получить актуальные коммерческие предложения от поставщиков/подрядчиков

Sheet Вопросы инженеру
A1: ЧЕРНОВОЙ ИНЖЕНЕРНЫЙ КОМПЛЕКТ. Черновой инженерный комплект. Не является рабочим КЖ-проектом и не предназначен для выполнения строительных работ без проверки, корректировки и выпуска лицензированным инженером-конструктором.
A6: ВОПРОСЫ ЛИЦЕНЗИРОВАННОМУ ИНЖЕНЕРУ-КОНСТРУКТОРУ
A7: № | B7: Вопрос
A8: 1 | B8: Какой класс защитного сооружения ЦЗ требуется/достижим для данного объекта и участка?
A9: 2 | B9: Достаточна ли толщина/армирование плит и стен с учётом фактической геологии и нагрузок?
A10: 3 | B10: Каков итоговый коэффициент устойчивости на всплытие и какие меры необходимы (утяжеление/анкеры/консоль)?
A11: 4 | B11: Какая система гидроизоляции («белая ванна») рекомендуется с учётом невозможности мембраны?
A12: 5 | B12: Достаточно ли предварительное усиление проёмов (Ø16) или требуется отдельный расчёт?
A13: 6 | B13: Какие нормативные документы (ДБН/ДСТУ) применимы в финальной редакции на дату проектирования?
A14: 7 | B14: Требуется ли антисейсмическое/динамическое усиление с учётом местных условий?
A15: 8 | B15: Каковы требования к защитным дверям (класс, избыточное давление) для выбранного класса защиты?
A17: ВОПРОСЫ ПОДРЯДЧИКУ ПЕРЕД ПОДПИСАНИЕМ ДОГОВОРА
A18: № | B18: Вопрос
A19: 1 | B19: Подтверждаете ли вы объёмы бетона/арматуры по факту рабочих чертежей (не по этому черновику)?
A20: 2 | B20: Какой конкретный завод-изготовитель бетона и способ доставки/подачи (миксер, насос) будет использован?
A21: 3 | B21: Какие сроки и условия гарантии на гидроизоляцию швов («белую ванну»)?
A22: 4 | B22: Какая модель защитно-герметичной и внутренней герметичной дверей предлагается и её паспортные данные?
A23: 5 | B23: Кто выполняет и кто несёт ответственность за качество рабочих швов бетонирования?
A24: 6 | B24: Предусмотрен ли технический надзор и промежуточная приёмка скрытых работ (арматура, гидроизоляция)?
A25: 7 | B25: Как будет организован водоотлив на период строительства при возможном притоке грунтовых вод?
A26: 8 | B26: Какова итоговая твёрдая/ориентировочная цена и порядок расчётов, привязанный к этапам работ?
